webint_system/__init__.py
webint_system/templates/__init__.py
webint_system/templates/addresses/__init__.py
webint_system/templates/addresses/domains.html
webint_system/templates/index.html
webint_system-0.0.29.dist-info/METADATA
webint_system-0.0.29.dist-info/entry_points.txt
webint_system-0.0.29.dist-info/WHEEL
webint_system-0.0.29.dist-info/RECORD
