Metadata-Version: 2.1
Name: webint-system
Version: 0.0.29
Summary: manage your website's system
Home-page: https://ragt.ag/code/projects/webint-system
License: AGPL-3.0-or-later
Author: Angelo Gladding
Author-email: angelo@ragt.ag
Requires-Python: >=3.10,<3.11
Classifier: License :: OSI Approved :: GNU Affero General Public License v3 or later (AGPLv3+)
Classifier: Programming Language :: Python :: 3
Classifier: Programming Language :: Python :: 3.10
Requires-Dist: webagt (>=0.0)
Requires-Dist: webint (>=0.0)
Project-URL: Documentation, https://ragt.ag/code/projects/webint-system/api
Project-URL: Repository, https://ragt.ag/code/projects/webint-system.git
